smallstep_py-0.1.1.dist-info/METADATA
smallstep_py-0.1.1.dist-info/WHEEL
smallstep_py-0.1.1.dist-info/licenses/LICENSE
step/__init__.py
step/models.py
step/step_cli.py
step/step_cli_parser.py
smallstep_py-0.1.1.dist-info/RECORD
